README.md
constants.py
get_CC_ATMs.py
setup.py
Coast_Capital_ATM_Locations.egg-info/PKG-INFO
Coast_Capital_ATM_Locations.egg-info/SOURCES.txt
Coast_Capital_ATM_Locations.egg-info/dependency_links.txt
Coast_Capital_ATM_Locations.egg-info/top_level.txt