Metadata-Version: 2.1
Name: Coast-Capital-ATM-Locations
Version: 0.0.1
Summary: Location of all Coast Capital ATMs including ones that are not at Coast Capital branches but can be used by Coast Capital members 
Home-page: https://github.com/GitGord/Coast-Capital-ATM-Locations
Author: Gordon Croft
Author-email: gordon.croft@telus.net
License: GNU General Public License V3
